contra_il6/__init__.py
contra_il6/architecture.py
contra_il6/default_config.yaml
contra_il6/feature_extractor.py
contra_il6/inference.py
contra_il6/run.py
contra_il6/utils.py
src/architecture.py
src/dataset.py
src/lightning_module.py
src/loss.py
src/metrics.py
src/utils.py
contra_il6-1.0.4.dist-info/METADATA
contra_il6-1.0.4.dist-info/WHEEL
contra_il6-1.0.4.dist-info/entry_points.txt
contra_il6-1.0.4.dist-info/top_level.txt
contra_il6-1.0.4.dist-info/RECORD
