Metadata-Version: 2.1
Name: contra_il6
Version: 1.0.4
Summary: A tool for predicting IL-6-inducing peptides
Requires-Python: >=3.8
Requires-Dist: click >=8.1
Requires-Dist: fair-esm ==2.0.0
Requires-Dist: bio-embeddings-duongttr[all] ==0.2.3
Requires-Dist: pyyaml >=6.0
